{
  "AnchorList": [],
  "AreaAnchorName": "LevelArea_P20332_F20332001_G438",
  "AudienceList": [],
  "BattleAreaList": [],
  "Category": "Custom",
  "ConflictIDList": [],
  "ConflictWhiteList": [],
  "CrowdList": [],
  "DistrictList": [],
  "GroupName": "MainMission1032902_27",
  "HoYoGroupType": "Container",
  "IsHoyoGroup": true,
  "MonsterList": [],
  "NPCList": [],
  "PathwayList": [],
  "PedestrianList": [],
  "PropList": [
    {
      "BridgeStateRotations": [],
      "CameraCenterEntityList": [],
      "CampID": 4,
      "CustomTriggerMap": {},
      "CustomTriggerMapV2": {},
      "DialogueGroups": [],
      "DialogueTriggerAngle": 120,
      "DialogueTriggerSkipFakeAvatar": true,
      "ID": 300001,
      "InteractTitle": {
        "Hash": 371857150
      },
      "LoadOnInitial": true,
      "LookAtPlayerTriggerRadius": 2,
      "Name": "Prop1",
      "OverrideHintRange": -1,
      "OverrideLockRaycastOffset": 1.5,
      "OverrideMapIconType": -1,
      "OverridePropName": {
        "Hash": 371857150
      },
      "OverrideSoundRange": -1,
      "PosX": 148.234,
      "PosY": 6.368,
      "PosZ": -396.929,
      "PropID": 103193,
      "RotY": 155.8318,
      "Scale": {
        "magnitude": 1.73205078,
        "normalized": {
          "magnitude": 0.99999994,
          "normalized": {
            "magnitude": 1.00000012,
            "sqrMagnitude": 1.00000024,
            "x": 0.5773503,
            "y": 0.5773503,
            "z": 0.5773503
          },
          "sqrMagnitude": 0.99999994,
          "x": 0.577350259,
          "y": 0.577350259,
          "z": 0.577350259
        },
        "sqrMagnitude": 3,
        "x": 1,
        "y": 1,
        "z": 1
      },
      "ServerInteractVerificationIDList": [],
      "SpawnConfig": {
        "EntitySpawnConfig": {
          "BlackInDistance": 25,
          "NeedBlackIn": true,
          "NeedFadeIn": true,
          "NeedFadeOut": true
        }
      },
      "State": "CustomState02",
      "TalkDialogGroupIDList": [],
      "TriggerValidGuest": {
        "LocalPlayer": true,
        "Teammember": true
      },
      "ValueSource": {}
    }
  ],
  "SaveType": "Reset",
  "SmartObjectList": [],
  "StreamingTemplateType": "Standard",
  "ValueSource": {},
  "WaypointList": []
}