{
  "AnchorList": [],
  "AreaAnchorName": "LevelArea_P10000_F10000000_G132",
  "BattleAreaList": [],
  "Category": "Mission",
  "ConflictIDList": [],
  "CrowdList": [],
  "DistrictList": [],
  "GroupName": "MainMission2010201_01",
  "LoadCondition": {
    "Conditions": [
      {
        "ID": 201020101,
        "Type": "SubMission"
      },
      {
        "ID": 201020101,
        "Phase": "Finish",
        "Type": "SubMission"
      }
    ],
    "Operation": "Or"
  },
  "MonsterList": [],
  "NPCList": [
    {
      "BoardShowList": [],
      "BornType": "Mission",
      "DefaultAnimationType": "FreeStyle",
      "DefaultIdleFreeStyleMotionID": 310010209,
      "DefaultLookAtMode": "LookPlayer",
      "Dialog": {
        "EnableDialogCamera": true,
        "LevelGraph": "Config/Level/NPCDialogue/P10000/F10000000_G132/DialogueMain_F10000000_G132_N400001.json",
        "PackList": []
      },
      "DialogueGroups": [],
      "DialogueTriggerAngle": 120,
      "DialogueTriggerSkipFakeAvatar": true,
      "ID": 400001,
      "InitialHiddenNodeList": [],
      "InteractIconType": "ChatIcon",
      "NPCID": 1001,
      "Name": "NPC1",
      "OverrideNPCName": {
        "Hash": 371857150
      },
      "OverrideNPCTitle": {
        "Hash": 371857150
      },
      "PosX": 5.946,
      "PosY": -0.000006,
      "PosZ": 7.969,
      "RotY": 93.1,
      "ServerInteractVerificationIDList": [],
      "SpawnConfig": {
        "CaptureDistanceTolerance": 10,
        "TryCapture": true
      },
      "TalkDialogGroupIDList": []
    },
    {
      "BoardShowList": [],
      "BornType": "Mission",
      "DefaultAnimationType": "FreeStyle",
      "DefaultLookAtMode": "LookPlayer",
      "DialogueGroups": [],
      "DialogueTriggerAngle": 120,
      "DialogueTriggerSkipFakeAvatar": true,
      "ID": 400002,
      "InitialHiddenNodeList": [],
      "InteractIconType": "ChatIcon",
      "LoadOnInitial": true,
      "NPCID": 100,
      "Name": "NPC2",
      "OverrideNPCName": {
        "Hash": 371857150
      },
      "OverrideNPCTitle": {
        "Hash": 371857150
      },
      "OverrideSeriesID": 100201,
      "PosX": 6.990301,
      "PosY": 1.63337,
      "PosZ": 11.01075,
      "ServerInteractVerificationIDList": [],
      "SpawnConfig": {
        "CaptureDistanceTolerance": 10,
        "TryCapture": true
      },
      "TalkDialogGroupIDList": []
    },
    {
      "BoardShowList": [],
      "BornType": "Mission",
      "DefaultAnimationType": "FreeStyle",
      "DefaultLookAtMode": "LookPlayer",
      "DialogueGroups": [],
      "DialogueTriggerAngle": 120,
      "DialogueTriggerSkipFakeAvatar": true,
      "ID": 400003,
      "InitialHiddenNodeList": [],
      "InteractIconType": "ChatIcon",
      "LoadOnInitial": true,
      "NPCID": 100,
      "Name": "NPC3",
      "OverrideNPCName": {
        "Hash": 371857150
      },
      "OverrideNPCTitle": {
        "Hash": 371857150
      },
      "OverrideSeriesID": 100301,
      "PosX": 6.990301,
      "PosY": 1.63337,
      "PosZ": 11.01075,
      "ServerInteractVerificationIDList": [],
      "SpawnConfig": {
        "CaptureDistanceTolerance": 10,
        "TryCapture": true
      },
      "TalkDialogGroupIDList": []
    }
  ],
  "OwnerMainMissionID": 2010201,
  "PathwayList": [],
  "PedestrianList": [],
  "PropList": [],
  "SaveType": "Reset",
  "SmartObjectList": [],
  "StreamingTemplateType": "Standard",
  "UnloadCondition": {
    "Conditions": [
      {
        "ID": 201020104,
        "Phase": "Finish",
        "Type": "SubMission"
      }
    ]
  },
  "WaypointList": []
}