{
  "AnchorList": [],
  "AreaAnchorName": "LevelArea_P20002_F20002001_G81",
  "BattleAreaList": [],
  "ConflictIDList": [],
  "CrowdList": [],
  "DistrictList": [],
  "GroupName": "CrowdControl",
  "LoadCondition": {
    "Conditions": [
      {
        "ID": 1000400,
        "Phase": "Finish"
      }
    ]
  },
  "MonsterList": [],
  "NPCList": [
    {
      "BoardShowList": [
        8
      ],
      "BornType": "Permanent",
      "DefaultAnimationType": "FreeStyle",
      "DefaultIdleFreeStyleMotionID": 100020299,
      "DefaultIdleStateName": "SitReading01Loop",
      "DialogueGroups": [],
      "DialogueTriggerAngle": 120,
      "DialogueTriggerSkipFakeAvatar": true,
      "ID": 400002,
      "InitialHiddenNodeList": [],
      "InteractIconType": "ChatIcon",
      "NPCID": 10214,
      "Name": "NPC2",
      "OverrideNPCName": {
        "Hash": 371857150
      },
      "OverrideNPCTitle": {
        "Hash": 371857150
      },
      "PosX": -0.748,
      "PosY": 18.61002,
      "PosZ": -107.432,
      "PossessionConfig": {
        "LocalScale": {
          "magnitude": 1.73205078,
          "normalized": {
            "magnitude": 0.99999994,
            "normalized": {
              "magnitude": 1.00000012,
              "sqrMagnitude": 1.00000024,
              "x": 0.5773503,
              "y": 0.5773503,
              "z": 0.5773503
            },
            "sqrMagnitude": 0.99999994,
            "x": 0.577350259,
            "y": 0.577350259,
            "z": 0.577350259
          },
          "sqrMagnitude": 3,
          "x": 1,
          "y": 1,
          "z": 1
        },
        "Name": "Possession_Book_A_03"
      },
      "RotY": 184.2972,
      "ServerInteractVerificationIDList": [],
      "TalkDialogGroupIDList": []
    },
    {
      "BoardShowList": [
        8
      ],
      "BornType": "Permanent",
      "DefaultAnimationType": "FreeStyle",
      "DefaultIdleFreeStyleMotionID": 100020301,
      "DefaultIdleStateName": "SitReading01Loop",
      "DialogueGroups": [],
      "DialogueTriggerAngle": 120,
      "DialogueTriggerSkipFakeAvatar": true,
      "ID": 400001,
      "InitialHiddenNodeList": [],
      "InteractIconType": "ChatIcon",
      "NPCID": 10209,
      "Name": "NPC1",
      "OverrideNPCName": {
        "Hash": 371857150
      },
      "OverrideNPCTitle": {
        "Hash": 371857150
      },
      "PosX": -1.565979,
      "PosY": 18.61002,
      "PosZ": -108.789,
      "RotY": 49.71183,
      "ServerInteractVerificationIDList": [],
      "TalkDialogGroupIDList": []
    },
    {
      "BoardShowList": [
        8
      ],
      "BornType": "Permanent",
      "DefaultAnimationType": "FreeStyle",
      "DefaultIdleFreeStyleMotionID": 100010236,
      "DefaultIdleStateName": "SitReading01Loop",
      "DefaultLookAtMode": "LookTarget",
      "DefaultLookAtTargetInfo": {
        "GroupID": 81,
        "InstanceID": 400004
      },
      "DialogueGroups": [],
      "DialogueTriggerAngle": 120,
      "DialogueTriggerSkipFakeAvatar": true,
      "ID": 400003,
      "InitialHiddenNodeList": [],
      "InteractIconType": "ChatIcon",
      "NPCID": 10119,
      "Name": "NPC3",
      "OverrideNPCName": {
        "Hash": 371857150
      },
      "OverrideNPCTitle": {
        "Hash": 371857150
      },
      "PosX": -7.621002,
      "PosY": 18.60994,
      "PosZ": -113.578,
      "RotY": 183.9846,
      "ServerInteractVerificationIDList": [],
      "TalkDialogGroupIDList": []
    },
    {
      "BoardShowList": [
        8
      ],
      "BornType": "Permanent",
      "DefaultAnimationType": "FreeStyle",
      "DefaultIdleFreeStyleMotionID": 100010230,
      "DefaultIdleStateName": "SitReading01Loop",
      "DefaultLookAtMode": "LookTarget",
      "DefaultLookAtTargetInfo": {
        "GroupID": 81,
        "InstanceID": 400003
      },
      "DialogueGroups": [],
      "DialogueTriggerAngle": 120,
      "DialogueTriggerSkipFakeAvatar": true,
      "ID": 400004,
      "InitialHiddenNodeList": [],
      "InteractIconType": "ChatIcon",
      "NPCID": 10117,
      "Name": "NPC4",
      "OverrideNPCName": {
        "Hash": 371857150
      },
      "OverrideNPCTitle": {
        "Hash": 371857150
      },
      "PosX": -8.384,
      "PosY": 18.61002,
      "PosZ": -114.326,
      "RotY": 27.97549,
      "ServerInteractVerificationIDList": [],
      "TalkDialogGroupIDList": []
    },
    {
      "BoardShowList": [
        8
      ],
      "BornType": "Permanent",
      "DefaultAnimationType": "FreeStyle",
      "DefaultIdleFreeStyleMotionID": 100010298,
      "DefaultIdleStateName": "SitReading01Loop",
      "DefaultLookAtMode": "LookTarget",
      "DefaultLookAtTargetInfo": {
        "GroupID": 81,
        "InstanceID": 400006
      },
      "DialogueGroups": [],
      "DialogueTriggerAngle": 120,
      "DialogueTriggerSkipFakeAvatar": true,
      "ID": 400005,
      "InitialHiddenNodeList": [],
      "InteractIconType": "ChatIcon",
      "NPCID": 10115,
      "Name": "NPC5",
      "OverrideNPCName": {
        "Hash": 371857150
      },
      "OverrideNPCTitle": {
        "Hash": 371857150
      },
      "PosX": -1.485,
      "PosY": 18.61002,
      "PosZ": -108.852,
      "RotY": 53.65325,
      "ServerInteractVerificationIDList": [],
      "TalkDialogGroupIDList": []
    },
    {
      "BoardShowList": [
        8
      ],
      "BornType": "Permanent",
      "DefaultAnimationType": "FreeStyle",
      "DefaultIdleFreeStyleMotionID": 100020302,
      "DefaultIdleStateName": "SitReading01Loop",
      "DefaultLookAtMode": "LookTarget",
      "DefaultLookAtTargetInfo": {
        "GroupID": 81,
        "InstanceID": 400005
      },
      "DialogueGroups": [],
      "DialogueTriggerAngle": 120,
      "DialogueTriggerSkipFakeAvatar": true,
      "ID": 400006,
      "InitialHiddenNodeList": [],
      "InteractIconType": "ChatIcon",
      "NPCID": 10217,
      "Name": "NPC6",
      "OverrideNPCName": {
        "Hash": 371857150
      },
      "OverrideNPCTitle": {
        "Hash": 371857150
      },
      "PosX": 0.001011,
      "PosY": 18.61002,
      "PosZ": -107.694,
      "RotY": 235.3202,
      "ServerInteractVerificationIDList": [],
      "TalkDialogGroupIDList": []
    },
    {
      "BoardShowList": [
        8
      ],
      "BornType": "Permanent",
      "DefaultAnimationType": "FreeStyle",
      "DefaultIdleFreeStyleMotionID": 100010209,
      "DefaultIdleStateName": "Akimbo01Loop",
      "DialogueGroups": [],
      "DialogueTriggerAngle": 120,
      "DialogueTriggerSkipFakeAvatar": true,
      "ID": 400007,
      "InitialHiddenNodeList": [],
      "InteractIconType": "ChatIcon",
      "NPCID": 10103,
      "Name": "NPC7",
      "OverrideNPCName": {
        "Hash": 1690540168
      },
      "OverrideNPCTitle": {
        "Hash": 371857150
      },
      "OverrideSeriesID": 4294967295,
      "PosX": -20.98999,
      "PosY": 18.66233,
      "PosZ": -98.83,
      "RotY": 16.75829,
      "ServerInteractVerificationIDList": [],
      "TalkDialogGroupIDList": []
    },
    {
      "BoardShowList": [
        8
      ],
      "BornType": "Permanent",
      "DefaultAnimationType": "FreeStyle",
      "DefaultIdleFreeStyleMotionID": 100010221,
      "DefaultIdleStateName": "Think01Loop",
      "DialogueGroups": [],
      "DialogueTriggerAngle": 120,
      "DialogueTriggerSkipFakeAvatar": true,
      "ID": 400008,
      "InitialHiddenNodeList": [],
      "InteractIconType": "ChatIcon",
      "NPCID": 10114,
      "Name": "NPC8",
      "OverrideNPCName": {
        "Hash": 371857150
      },
      "OverrideNPCTitle": {
        "Hash": 371857150
      },
      "PosX": -22.20996,
      "PosY": 18.66233,
      "PosZ": -98.23999,
      "RotY": 47.55782,
      "ServerInteractVerificationIDList": [],
      "TalkDialogGroupIDList": []
    },
    {
      "BoardShowList": [
        8
      ],
      "BornType": "Permanent",
      "DefaultAnimationType": "FreeStyle",
      "DefaultIdleFreeStyleMotionID": 100010231,
      "DefaultIdleStateName": "HoldArm01Loop",
      "DialogueGroups": [],
      "DialogueTriggerAngle": 120,
      "DialogueTriggerSkipFakeAvatar": true,
      "ID": 400009,
      "InitialHiddenNodeList": [],
      "InteractIconType": "ChatIcon",
      "NPCID": 10108,
      "Name": "NPC9",
      "OverrideNPCName": {
        "Hash": 1690540168
      },
      "OverrideNPCTitle": {
        "Hash": 371857150
      },
      "PosX": -23.95999,
      "PosY": 18.61003,
      "PosZ": -104.76,
      "RotY": 44.70749,
      "ServerInteractVerificationIDList": [],
      "TalkDialogGroupIDList": []
    },
    {
      "BoardShowList": [
        8
      ],
      "BornType": "Permanent",
      "DefaultAnimationType": "FreeStyle",
      "DefaultIdleFreeStyleMotionID": 100010301,
      "DefaultIdleStateName": "SitReading01Loop",
      "DefaultLookAtMode": "LookTarget",
      "DefaultLookAtTargetInfo": {
        "GroupID": 81,
        "InstanceID": 400011
      },
      "DialogueGroups": [],
      "DialogueTriggerAngle": 120,
      "DialogueTriggerSkipFakeAvatar": true,
      "ID": 400010,
      "InitialHiddenNodeList": [],
      "InteractIconType": "ChatIcon",
      "NPCID": 10113,
      "Name": "NPC10",
      "OverrideNPCName": {
        "Hash": 371857150
      },
      "OverrideNPCTitle": {
        "Hash": 371857150
      },
      "PosX": -4.578,
      "PosY": 18.61002,
      "PosZ": -114.738,
      "RotY": 75.44295,
      "ServerInteractVerificationIDList": [],
      "TalkDialogGroupIDList": []
    },
    {
      "BoardShowList": [
        8
      ],
      "BornType": "Permanent",
      "DefaultAnimationType": "FreeStyle",
      "DefaultIdleFreeStyleMotionID": 100020231,
      "DefaultIdleStateName": "SitReading01Loop",
      "DefaultLookAtMode": "LookTarget",
      "DefaultLookAtTargetInfo": {
        "GroupID": 81,
        "InstanceID": 400010
      },
      "DialogueGroups": [],
      "DialogueTriggerAngle": 120,
      "DialogueTriggerSkipFakeAvatar": true,
      "ID": 400011,
      "InitialHiddenNodeList": [],
      "InteractIconType": "ChatIcon",
      "NPCID": 10217,
      "Name": "NPC11",
      "OverrideNPCName": {
        "Hash": 371857150
      },
      "OverrideNPCTitle": {
        "Hash": 371857150
      },
      "PosX": -3.287,
      "PosY": 18.61002,
      "PosZ": -115.028,
      "RotY": 284.2185,
      "ServerInteractVerificationIDList": [],
      "TalkDialogGroupIDList": []
    }
  ],
  "PathwayList": [],
  "PedestrianList": [],
  "PropList": [
    {
      "BridgeStateRotations": [],
      "CampID": 4,
      "CustomTriggerMap": {},
      "CustomTriggerMapV2": {},
      "DialogueGroups": [],
      "DialogueTriggerAngle": 120,
      "DialogueTriggerSkipFakeAvatar": true,
      "ID": 300001,
      "InitLevelGraph": "Config/Level/CrowdBubble/20002001/Crowd_20002001.json",
      "InteractTitle": {
        "Hash": 371857150
      },
      "IsOverrideInitLevelGraph": true,
      "LookAtPlayerTriggerRadius": 2,
      "Name": "Prop1",
      "OverrideHintRange": -1,
      "OverrideLockRaycastOffset": 1.5,
      "OverrideMapIconType": -1,
      "OverridePropName": {
        "Hash": 371857150
      },
      "OverrideSoundRange": -1,
      "PosX": -5.774659,
      "PosY": 18.64041,
      "PosZ": -108.9541,
      "PropID": 100,
      "Scale": {
        "magnitude": 1.73205078,
        "normalized": {
          "magnitude": 0.99999994,
          "normalized": {
            "magnitude": 1.00000012,
            "sqrMagnitude": 1.00000024,
            "x": 0.5773503,
            "y": 0.5773503,
            "z": 0.5773503
          },
          "sqrMagnitude": 0.99999994,
          "x": 0.577350259,
          "y": 0.577350259,
          "z": 0.577350259
        },
        "sqrMagnitude": 3,
        "x": 1,
        "y": 1,
        "z": 1
      },
      "ServerInteractVerificationIDList": [],
      "TalkDialogGroupIDList": []
    },
    {
      "BridgeStateRotations": [],
      "CampID": 4,
      "CustomTriggerMap": {},
      "CustomTriggerMapV2": {},
      "DialogueGroups": [],
      "DialogueTriggerAngle": 120,
      "DialogueTriggerSkipFakeAvatar": true,
      "ID": 300002,
      "InitLevelGraph": "Config/Level/CrowdBubble/MunicipalChat_Play_Stop_Template.json",
      "InteractTitle": {
        "Hash": 371857150
      },
      "IsOverrideInitLevelGraph": true,
      "LookAtPlayerTriggerRadius": 2,
      "Name": "Prop2",
      "OverrideHintRange": -1,
      "OverrideLockRaycastOffset": 1.5,
      "OverrideMapIconType": -1,
      "OverridePropName": {
        "Hash": 371857150
      },
      "OverrideSoundRange": -1,
      "PosX": -1.71,
      "PosY": 18.64041,
      "PosZ": -107.895,
      "PropID": 100,
      "Scale": {
        "magnitude": 1.73205078,
        "normalized": {
          "magnitude": 0.99999994,
          "normalized": {
            "magnitude": 1.00000012,
            "sqrMagnitude": 1.00000024,
            "x": 0.5773503,
            "y": 0.5773503,
            "z": 0.5773503
          },
          "sqrMagnitude": 0.99999994,
          "x": 0.577350259,
          "y": 0.577350259,
          "z": 0.577350259
        },
        "sqrMagnitude": 3,
        "x": 1,
        "y": 1,
        "z": 1
      },
      "ServerInteractVerificationIDList": [],
      "SpawnConfig": {
        "EntitySpawnConfig": {
          "BlackInDistance": 25,
          "NeedBlackIn": true,
          "NeedFadeIn": true,
          "NeedFadeOut": true
        }
      },
      "TalkDialogGroupIDList": [],
      "Trigger": {
        "DimX": 1,
        "DimY": 1,
        "DimZ": 1,
        "PointList": [],
        "Radius": 3.5
      },
      "TriggerValidGuest": {
        "LocalPlayer": true,
        "Teammember": true
      },
      "ValueSource": {
        "SharedValues": [
          {
            "$type": "RPG.GameCore.SharedString, RPG.GameCore.Config",
            "Key": "PlayMunicipalChatPath",
            "Value": "Config/Level/MunicipalChatConfig/F20002001/MunicipalChatConfig_F20002001_0001.json"
          },
          {
            "$type": "RPG.GameCore.SharedString, RPG.GameCore.Config",
            "Key": "PlayMunicipalChatName",
            "Value": "MunicipalChatConfig_F20002001_0001"
          },
          {
            "$type": "RPG.GameCore.SharedJsonConfigList, RPG.GameCore.Config",
            "Key": "PlayMunicipalChatCharacterList",
            "Value": [
              {
                "$type": "RPG.GameCore.MunicipalChatEntityInfo, RPG.GameCore.Config",
                "GroupInstanceID": 400001,
                "UniqueName": "1"
              },
              {
                "$type": "RPG.GameCore.MunicipalChatEntityInfo, RPG.GameCore.Config",
                "GroupInstanceID": 400002,
                "UniqueName": "2"
              }
            ]
          }
        ],
        "Values": [
          {
            "$type": "RPG.GameCore.SharedString, RPG.GameCore.Config",
            "Key": "PlayMunicipalChatPath",
            "Value": "Config/Level/MunicipalChatConfig/F20002001/MunicipalChatConfig_F20002001_0001.json"
          },
          {
            "$type": "RPG.GameCore.SharedString, RPG.GameCore.Config",
            "Key": "PlayMunicipalChatName",
            "Value": "MunicipalChatConfig_F20002001_0001"
          },
          {
            "$type": "RPG.GameCore.SharedJsonConfigList, RPG.GameCore.Config",
            "Key": "PlayMunicipalChatCharacterList",
            "Value": [
              {
                "$type": "RPG.GameCore.MunicipalChatEntityInfo, RPG.GameCore.Config",
                "GroupInstanceID": 400001,
                "UniqueName": "1"
              },
              {
                "$type": "RPG.GameCore.MunicipalChatEntityInfo, RPG.GameCore.Config",
                "GroupInstanceID": 400002,
                "UniqueName": "2"
              }
            ]
          }
        ]
      }
    },
    {
      "BridgeStateRotations": [],
      "CampID": 4,
      "CustomTriggerMap": {},
      "CustomTriggerMapV2": {},
      "DialogueGroups": [],
      "DialogueTriggerAngle": 120,
      "DialogueTriggerSkipFakeAvatar": true,
      "ID": 300003,
      "InitLevelGraph": "Config/Level/CrowdBubble/MunicipalChat_Play_Stop_Template.json",
      "InteractTitle": {
        "Hash": 371857150
      },
      "IsOverrideInitLevelGraph": true,
      "LookAtPlayerTriggerRadius": 2,
      "Name": "Prop3",
      "OverrideHintRange": -1,
      "OverrideLockRaycastOffset": 1.5,
      "OverrideMapIconType": -1,
      "OverridePropName": {
        "Hash": 371857150
      },
      "OverrideSoundRange": -1,
      "PosX": -7.87,
      "PosY": 18.64041,
      "PosZ": -114.69,
      "PropID": 100,
      "RotX": 0.983715,
      "RotY": 3.46659,
      "RotZ": 2.150003,
      "Scale": {
        "magnitude": 1.73205078,
        "normalized": {
          "magnitude": 0.99999994,
          "normalized": {
            "magnitude": 1.00000012,
            "sqrMagnitude": 1.00000024,
            "x": 0.5773503,
            "y": 0.5773503,
            "z": 0.5773503
          },
          "sqrMagnitude": 0.99999994,
          "x": 0.577350259,
          "y": 0.577350259,
          "z": 0.577350259
        },
        "sqrMagnitude": 3,
        "x": 1,
        "y": 1,
        "z": 1
      },
      "ServerInteractVerificationIDList": [],
      "SpawnConfig": {
        "EntitySpawnConfig": {
          "BlackInDistance": 25,
          "NeedBlackIn": true,
          "NeedFadeIn": true,
          "NeedFadeOut": true
        }
      },
      "TalkDialogGroupIDList": [],
      "Trigger": {
        "DimX": 1,
        "DimY": 1,
        "DimZ": 1,
        "PointList": [],
        "Radius": 3.5
      },
      "TriggerValidGuest": {
        "LocalPlayer": true,
        "Teammember": true
      },
      "ValueSource": {
        "SharedValues": [
          {
            "$type": "RPG.GameCore.SharedString, RPG.GameCore.Config",
            "Key": "PlayMunicipalChatPath",
            "Value": "Config/Level/MunicipalChatConfig/F20002001/MunicipalChatConfig_F20002001_0002.json"
          },
          {
            "$type": "RPG.GameCore.SharedString, RPG.GameCore.Config",
            "Key": "PlayMunicipalChatName",
            "Value": "MunicipalChatConfig_F20002001_0002"
          },
          {
            "$type": "RPG.GameCore.SharedJsonConfigList, RPG.GameCore.Config",
            "Key": "PlayMunicipalChatCharacterList",
            "Value": [
              {
                "$type": "RPG.GameCore.MunicipalChatEntityInfo, RPG.GameCore.Config",
                "GroupInstanceID": 400003,
                "UniqueName": "1"
              },
              {
                "$type": "RPG.GameCore.MunicipalChatEntityInfo, RPG.GameCore.Config",
                "GroupInstanceID": 400004,
                "UniqueName": "2"
              }
            ]
          }
        ],
        "Values": [
          {
            "$type": "RPG.GameCore.SharedString, RPG.GameCore.Config",
            "Key": "PlayMunicipalChatPath",
            "Value": "Config/Level/MunicipalChatConfig/F20002001/MunicipalChatConfig_F20002001_0002.json"
          },
          {
            "$type": "RPG.GameCore.SharedString, RPG.GameCore.Config",
            "Key": "PlayMunicipalChatName",
            "Value": "MunicipalChatConfig_F20002001_0002"
          },
          {
            "$type": "RPG.GameCore.SharedJsonConfigList, RPG.GameCore.Config",
            "Key": "PlayMunicipalChatCharacterList",
            "Value": [
              {
                "$type": "RPG.GameCore.MunicipalChatEntityInfo, RPG.GameCore.Config",
                "GroupInstanceID": 400003,
                "UniqueName": "1"
              },
              {
                "$type": "RPG.GameCore.MunicipalChatEntityInfo, RPG.GameCore.Config",
                "GroupInstanceID": 400004,
                "UniqueName": "2"
              }
            ]
          }
        ]
      }
    },
    {
      "BridgeStateRotations": [],
      "CampID": 4,
      "CustomTriggerMap": {},
      "CustomTriggerMapV2": {},
      "DialogueGroups": [],
      "DialogueTriggerAngle": 120,
      "DialogueTriggerSkipFakeAvatar": true,
      "ID": 300004,
      "InitLevelGraph": "Config/Level/CrowdBubble/MunicipalChat_Play_Stop_Template.json",
      "InteractTitle": {
        "Hash": 371857150
      },
      "IsOverrideInitLevelGraph": true,
      "LookAtPlayerTriggerRadius": 2,
      "Name": "Prop4",
      "OverrideHintRange": -1,
      "OverrideLockRaycastOffset": 1.5,
      "OverrideMapIconType": -1,
      "OverridePropName": {
        "Hash": 371857150
      },
      "OverrideSoundRange": -1,
      "PosX": -0.781,
      "PosY": 18.774,
      "PosZ": -108.24,
      "PropID": 100,
      "RotX": 0.983715,
      "RotY": 3.46659,
      "RotZ": 2.150003,
      "Scale": {
        "magnitude": 1.73205078,
        "normalized": {
          "magnitude": 0.99999994,
          "normalized": {
            "magnitude": 1.00000012,
            "sqrMagnitude": 1.00000024,
            "x": 0.5773503,
            "y": 0.5773503,
            "z": 0.5773503
          },
          "sqrMagnitude": 0.99999994,
          "x": 0.577350259,
          "y": 0.577350259,
          "z": 0.577350259
        },
        "sqrMagnitude": 3,
        "x": 1,
        "y": 1,
        "z": 1
      },
      "ServerInteractVerificationIDList": [],
      "SpawnConfig": {
        "EntitySpawnConfig": {
          "BlackInDistance": 25,
          "NeedBlackIn": true,
          "NeedFadeIn": true,
          "NeedFadeOut": true
        }
      },
      "TalkDialogGroupIDList": [],
      "Trigger": {
        "DimX": 1,
        "DimY": 1,
        "DimZ": 1,
        "PointList": [],
        "Radius": 3.5
      },
      "TriggerValidGuest": {
        "LocalPlayer": true,
        "Teammember": true
      },
      "ValueSource": {
        "SharedValues": [
          {
            "$type": "RPG.GameCore.SharedString, RPG.GameCore.Config",
            "Key": "PlayMunicipalChatPath",
            "Value": "Config/Level/MunicipalChatConfig/F20002001/MunicipalChatConfig_F20002001_0003.json"
          },
          {
            "$type": "RPG.GameCore.SharedString, RPG.GameCore.Config",
            "Key": "PlayMunicipalChatName",
            "Value": "MunicipalChatConfig_F20002001_0003"
          },
          {
            "$type": "RPG.GameCore.SharedJsonConfigList, RPG.GameCore.Config",
            "Key": "PlayMunicipalChatCharacterList",
            "Value": [
              {
                "$type": "RPG.GameCore.MunicipalChatEntityInfo, RPG.GameCore.Config",
                "GroupInstanceID": 400005,
                "UniqueName": "1"
              },
              {
                "$type": "RPG.GameCore.MunicipalChatEntityInfo, RPG.GameCore.Config",
                "GroupInstanceID": 400006,
                "UniqueName": "2"
              }
            ]
          }
        ],
        "Values": [
          {
            "$type": "RPG.GameCore.SharedString, RPG.GameCore.Config",
            "Key": "PlayMunicipalChatPath",
            "Value": "Config/Level/MunicipalChatConfig/F20002001/MunicipalChatConfig_F20002001_0003.json"
          },
          {
            "$type": "RPG.GameCore.SharedString, RPG.GameCore.Config",
            "Key": "PlayMunicipalChatName",
            "Value": "MunicipalChatConfig_F20002001_0003"
          },
          {
            "$type": "RPG.GameCore.SharedJsonConfigList, RPG.GameCore.Config",
            "Key": "PlayMunicipalChatCharacterList",
            "Value": [
              {
                "$type": "RPG.GameCore.MunicipalChatEntityInfo, RPG.GameCore.Config",
                "GroupInstanceID": 400005,
                "UniqueName": "1"
              },
              {
                "$type": "RPG.GameCore.MunicipalChatEntityInfo, RPG.GameCore.Config",
                "GroupInstanceID": 400006,
                "UniqueName": "2"
              }
            ]
          }
        ]
      }
    },
    {
      "BridgeStateRotations": [],
      "CampID": 4,
      "CustomTriggerMap": {},
      "CustomTriggerMapV2": {},
      "DialogueGroups": [],
      "DialogueTriggerAngle": 120,
      "DialogueTriggerSkipFakeAvatar": true,
      "ID": 300005,
      "InitLevelGraph": "Config/Level/CrowdBubble/MunicipalChat_Play_Stop_Template.json",
      "InteractTitle": {
        "Hash": 371857150
      },
      "IsOverrideInitLevelGraph": true,
      "LookAtPlayerTriggerRadius": 2,
      "Name": "Prop5",
      "OverrideHintRange": -1,
      "OverrideLockRaycastOffset": 1.5,
      "OverrideMapIconType": -1,
      "OverridePropName": {
        "Hash": 371857150
      },
      "OverrideSoundRange": -1,
      "PosX": -21.606,
      "PosY": 18.597,
      "PosZ": -98.599,
      "PropID": 100,
      "RotX": 0.289003,
      "RotY": 21.02407,
      "RotZ": 2.346545,
      "Scale": {
        "magnitude": 1.73205078,
        "normalized": {
          "magnitude": 0.99999994,
          "normalized": {
            "magnitude": 1.00000012,
            "sqrMagnitude": 1.00000024,
            "x": 0.5773503,
            "y": 0.5773503,
            "z": 0.5773503
          },
          "sqrMagnitude": 0.99999994,
          "x": 0.577350259,
          "y": 0.577350259,
          "z": 0.577350259
        },
        "sqrMagnitude": 3,
        "x": 1,
        "y": 1,
        "z": 1
      },
      "ServerInteractVerificationIDList": [],
      "SpawnConfig": {
        "EntitySpawnConfig": {
          "BlackInDistance": 25,
          "NeedBlackIn": true,
          "NeedFadeIn": true,
          "NeedFadeOut": true
        }
      },
      "TalkDialogGroupIDList": [],
      "Trigger": {
        "DimX": 1,
        "DimY": 1,
        "DimZ": 1,
        "PointList": [],
        "Radius": 3.5
      },
      "TriggerValidGuest": {
        "LocalPlayer": true,
        "Teammember": true
      },
      "ValueSource": {
        "SharedValues": [
          {
            "$type": "RPG.GameCore.SharedString, RPG.GameCore.Config",
            "Key": "PlayMunicipalChatPath",
            "Value": "Config/Level/MunicipalChatConfig/F20002001/MunicipalChatConfig_F20002001_0004.json"
          },
          {
            "$type": "RPG.GameCore.SharedString, RPG.GameCore.Config",
            "Key": "PlayMunicipalChatName",
            "Value": "MunicipalChatConfig_F20002001_0004"
          },
          {
            "$type": "RPG.GameCore.SharedJsonConfigList, RPG.GameCore.Config",
            "Key": "PlayMunicipalChatCharacterList",
            "Value": [
              {
                "$type": "RPG.GameCore.MunicipalChatEntityInfo, RPG.GameCore.Config",
                "GroupInstanceID": 400007,
                "UniqueName": "1"
              },
              {
                "$type": "RPG.GameCore.MunicipalChatEntityInfo, RPG.GameCore.Config",
                "GroupInstanceID": 400008,
                "UniqueName": "2"
              }
            ]
          }
        ],
        "Values": [
          {
            "$type": "RPG.GameCore.SharedString, RPG.GameCore.Config",
            "Key": "PlayMunicipalChatPath",
            "Value": "Config/Level/MunicipalChatConfig/F20002001/MunicipalChatConfig_F20002001_0004.json"
          },
          {
            "$type": "RPG.GameCore.SharedString, RPG.GameCore.Config",
            "Key": "PlayMunicipalChatName",
            "Value": "MunicipalChatConfig_F20002001_0004"
          },
          {
            "$type": "RPG.GameCore.SharedJsonConfigList, RPG.GameCore.Config",
            "Key": "PlayMunicipalChatCharacterList",
            "Value": [
              {
                "$type": "RPG.GameCore.MunicipalChatEntityInfo, RPG.GameCore.Config",
                "GroupInstanceID": 400007,
                "UniqueName": "1"
              },
              {
                "$type": "RPG.GameCore.MunicipalChatEntityInfo, RPG.GameCore.Config",
                "GroupInstanceID": 400008,
                "UniqueName": "2"
              }
            ]
          }
        ]
      }
    },
    {
      "BridgeStateRotations": [],
      "CampID": 4,
      "CustomTriggerMap": {},
      "CustomTriggerMapV2": {},
      "DialogueGroups": [],
      "DialogueTriggerAngle": 120,
      "DialogueTriggerSkipFakeAvatar": true,
      "ID": 300008,
      "InitLevelGraph": "Config/Level/CrowdBubble/Crowd_Conversation_Template.json",
      "InteractTitle": {
        "Hash": 371857150
      },
      "IsOverrideInitLevelGraph": true,
      "LookAtPlayerTriggerRadius": 2,
      "Name": "Prop8",
      "OverrideHintRange": -1,
      "OverrideLockRaycastOffset": 1.5,
      "OverrideMapIconType": -1,
      "OverridePropName": {
        "Hash": 371857150
      },
      "OverrideSoundRange": -1,
      "PosX": -21.606,
      "PosY": 18.597,
      "PosZ": -98.599,
      "PropID": 100,
      "RotX": 0.289003,
      "RotY": 21.02407,
      "RotZ": 2.346545,
      "Scale": {
        "magnitude": 1.73205078,
        "normalized": {
          "magnitude": 0.99999994,
          "normalized": {
            "magnitude": 1.00000012,
            "sqrMagnitude": 1.00000024,
            "x": 0.5773503,
            "y": 0.5773503,
            "z": 0.5773503
          },
          "sqrMagnitude": 0.99999994,
          "x": 0.577350259,
          "y": 0.577350259,
          "z": 0.577350259
        },
        "sqrMagnitude": 3,
        "x": 1,
        "y": 1,
        "z": 1
      },
      "ServerInteractVerificationIDList": [],
      "SpawnConfig": {
        "EntitySpawnConfig": {
          "BlackInDistance": 25,
          "NeedBlackIn": true,
          "NeedFadeIn": true,
          "NeedFadeOut": true
        }
      },
      "TalkDialogGroupIDList": [],
      "Trigger": {
        "DimX": 1,
        "DimY": 1,
        "DimZ": 1,
        "PointList": [],
        "Radius": 2
      },
      "TriggerValidGuest": {
        "LocalPlayer": true,
        "Teammember": true
      },
      "ValueSource": {
        "SharedValues": [
          {
            "$type": "RPG.GameCore.SharedString, RPG.GameCore.Config",
            "Key": "PlayPerformanceE",
            "Value": "500061001"
          }
        ],
        "Values": [
          {
            "$type": "RPG.GameCore.SharedString, RPG.GameCore.Config",
            "Key": "PlayPerformanceE",
            "Value": "500061001"
          }
        ]
      }
    },
    {
      "BridgeStateRotations": [],
      "CampID": 4,
      "CustomTriggerMap": {},
      "CustomTriggerMapV2": {},
      "DialogueGroups": [],
      "DialogueTriggerAngle": 120,
      "DialogueTriggerSkipFakeAvatar": true,
      "ID": 300007,
      "InitLevelGraph": "Config/Level/CrowdBubble/MunicipalChat_Play_Stop_Template.json",
      "InteractTitle": {
        "Hash": 371857150
      },
      "IsOverrideInitLevelGraph": true,
      "LookAtPlayerTriggerRadius": 2,
      "Name": "Prop7",
      "OverrideHintRange": -1,
      "OverrideLockRaycastOffset": 1.5,
      "OverrideMapIconType": -1,
      "OverridePropName": {
        "Hash": 371857150
      },
      "OverrideSoundRange": -1,
      "PosX": -23.988,
      "PosY": 18.632,
      "PosZ": -104.798,
      "PropID": 100,
      "RotX": 0.289003,
      "RotY": 21.02407,
      "RotZ": 2.346545,
      "Scale": {
        "magnitude": 1.73205078,
        "normalized": {
          "magnitude": 0.99999994,
          "normalized": {
            "magnitude": 1.00000012,
            "sqrMagnitude": 1.00000024,
            "x": 0.5773503,
            "y": 0.5773503,
            "z": 0.5773503
          },
          "sqrMagnitude": 0.99999994,
          "x": 0.577350259,
          "y": 0.577350259,
          "z": 0.577350259
        },
        "sqrMagnitude": 3,
        "x": 1,
        "y": 1,
        "z": 1
      },
      "ServerInteractVerificationIDList": [],
      "SpawnConfig": {
        "EntitySpawnConfig": {
          "BlackInDistance": 25,
          "NeedBlackIn": true,
          "NeedFadeIn": true,
          "NeedFadeOut": true
        }
      },
      "TalkDialogGroupIDList": [],
      "Trigger": {
        "DimX": 1,
        "DimY": 1,
        "DimZ": 1,
        "PointList": [],
        "Radius": 3.5
      },
      "TriggerValidGuest": {
        "LocalPlayer": true,
        "Teammember": true
      },
      "ValueSource": {
        "SharedValues": [
          {
            "$type": "RPG.GameCore.SharedString, RPG.GameCore.Config",
            "Key": "PlayMunicipalChatPath",
            "Value": "Config/Level/MunicipalChatConfig/F20002001/MunicipalChatConfig_F20002001_0005.json"
          },
          {
            "$type": "RPG.GameCore.SharedString, RPG.GameCore.Config",
            "Key": "PlayMunicipalChatName",
            "Value": "MunicipalChatConfig_F20002001_0005"
          },
          {
            "$type": "RPG.GameCore.SharedJsonConfigList, RPG.GameCore.Config",
            "Key": "PlayMunicipalChatCharacterList",
            "Value": [
              {
                "$type": "RPG.GameCore.MunicipalChatEntityInfo, RPG.GameCore.Config",
                "GroupInstanceID": 400009,
                "UniqueName": "1"
              }
            ]
          }
        ],
        "Values": [
          {
            "$type": "RPG.GameCore.SharedString, RPG.GameCore.Config",
            "Key": "PlayMunicipalChatPath",
            "Value": "Config/Level/MunicipalChatConfig/F20002001/MunicipalChatConfig_F20002001_0005.json"
          },
          {
            "$type": "RPG.GameCore.SharedString, RPG.GameCore.Config",
            "Key": "PlayMunicipalChatName",
            "Value": "MunicipalChatConfig_F20002001_0005"
          },
          {
            "$type": "RPG.GameCore.SharedJsonConfigList, RPG.GameCore.Config",
            "Key": "PlayMunicipalChatCharacterList",
            "Value": [
              {
                "$type": "RPG.GameCore.MunicipalChatEntityInfo, RPG.GameCore.Config",
                "GroupInstanceID": 400009,
                "UniqueName": "1"
              }
            ]
          }
        ]
      }
    },
    {
      "BridgeStateRotations": [],
      "CampID": 4,
      "CustomTriggerMap": {},
      "CustomTriggerMapV2": {},
      "DialogueGroups": [],
      "DialogueTriggerAngle": 120,
      "DialogueTriggerSkipFakeAvatar": true,
      "ID": 300009,
      "InitLevelGraph": "Config/Level/CrowdBubble/Crowd_Conversation_Template.json",
      "InteractTitle": {
        "Hash": 371857150
      },
      "IsOverrideInitLevelGraph": true,
      "LookAtPlayerTriggerRadius": 2,
      "Name": "Prop9",
      "OverrideHintRange": -1,
      "OverrideLockRaycastOffset": 1.5,
      "OverrideMapIconType": -1,
      "OverridePropName": {
        "Hash": 371857150
      },
      "OverrideSoundRange": -1,
      "PosX": -23.988,
      "PosY": 18.632,
      "PosZ": -104.798,
      "PropID": 100,
      "RotX": 0.289003,
      "RotY": 21.02407,
      "RotZ": 2.346545,
      "Scale": {
        "magnitude": 1.73205078,
        "normalized": {
          "magnitude": 0.99999994,
          "normalized": {
            "magnitude": 1.00000012,
            "sqrMagnitude": 1.00000024,
            "x": 0.5773503,
            "y": 0.5773503,
            "z": 0.5773503
          },
          "sqrMagnitude": 0.99999994,
          "x": 0.577350259,
          "y": 0.577350259,
          "z": 0.577350259
        },
        "sqrMagnitude": 3,
        "x": 1,
        "y": 1,
        "z": 1
      },
      "ServerInteractVerificationIDList": [],
      "SpawnConfig": {
        "EntitySpawnConfig": {
          "BlackInDistance": 25,
          "NeedBlackIn": true,
          "NeedFadeIn": true,
          "NeedFadeOut": true
        }
      },
      "TalkDialogGroupIDList": [],
      "Trigger": {
        "DimX": 1,
        "DimY": 1,
        "DimZ": 1,
        "PointList": [],
        "Radius": 2
      },
      "TriggerValidGuest": {
        "LocalPlayer": true,
        "Teammember": true
      },
      "ValueSource": {
        "SharedValues": [
          {
            "$type": "RPG.GameCore.SharedString, RPG.GameCore.Config",
            "Key": "PlayPerformanceE",
            "Value": "500061002"
          }
        ],
        "Values": [
          {
            "$type": "RPG.GameCore.SharedString, RPG.GameCore.Config",
            "Key": "PlayPerformanceE",
            "Value": "500061002"
          }
        ]
      }
    },
    {
      "BridgeStateRotations": [],
      "CampID": 4,
      "CustomTriggerMap": {},
      "CustomTriggerMapV2": {},
      "DialogueGroups": [],
      "DialogueTriggerAngle": 120,
      "DialogueTriggerSkipFakeAvatar": true,
      "ID": 300006,
      "InitLevelGraph": "Config/Level/CrowdBubble/MunicipalChat_Play_Stop_Template.json",
      "InteractTitle": {
        "Hash": 371857150
      },
      "IsOverrideInitLevelGraph": true,
      "LookAtPlayerTriggerRadius": 2,
      "Name": "Prop6",
      "OverrideHintRange": -1,
      "OverrideLockRaycastOffset": 1.5,
      "OverrideMapIconType": -1,
      "OverridePropName": {
        "Hash": 371857150
      },
      "OverrideSoundRange": -1,
      "PosX": -4.41,
      "PosY": 18.76,
      "PosZ": -114.89,
      "PropID": 100,
      "RotX": 0.983715,
      "RotY": 3.46659,
      "RotZ": 2.150003,
      "Scale": {
        "magnitude": 1.73205078,
        "normalized": {
          "magnitude": 0.99999994,
          "normalized": {
            "magnitude": 1.00000012,
            "sqrMagnitude": 1.00000024,
            "x": 0.5773503,
            "y": 0.5773503,
            "z": 0.5773503
          },
          "sqrMagnitude": 0.99999994,
          "x": 0.577350259,
          "y": 0.577350259,
          "z": 0.577350259
        },
        "sqrMagnitude": 3,
        "x": 1,
        "y": 1,
        "z": 1
      },
      "ServerInteractVerificationIDList": [],
      "SpawnConfig": {
        "EntitySpawnConfig": {
          "BlackInDistance": 25,
          "NeedBlackIn": true,
          "NeedFadeIn": true,
          "NeedFadeOut": true
        }
      },
      "TalkDialogGroupIDList": [],
      "Trigger": {
        "DimX": 1,
        "DimY": 1,
        "DimZ": 1,
        "PointList": [],
        "Radius": 3.5
      },
      "TriggerValidGuest": {
        "LocalPlayer": true,
        "Teammember": true
      },
      "ValueSource": {
        "SharedValues": [
          {
            "$type": "RPG.GameCore.SharedString, RPG.GameCore.Config",
            "Key": "PlayMunicipalChatPath",
            "Value": "Config/Level/MunicipalChatConfig/F20002001/MunicipalChatConfig_F20002001_0006.json"
          },
          {
            "$type": "RPG.GameCore.SharedString, RPG.GameCore.Config",
            "Key": "PlayMunicipalChatName",
            "Value": "MunicipalChatConfig_F20002001_0006"
          },
          {
            "$type": "RPG.GameCore.SharedJsonConfigList, RPG.GameCore.Config",
            "Key": "PlayMunicipalChatCharacterList",
            "Value": [
              {
                "$type": "RPG.GameCore.MunicipalChatEntityInfo, RPG.GameCore.Config",
                "GroupInstanceID": 400010,
                "UniqueName": "1"
              },
              {
                "$type": "RPG.GameCore.MunicipalChatEntityInfo, RPG.GameCore.Config",
                "GroupInstanceID": 400011,
                "UniqueName": "2"
              }
            ]
          }
        ],
        "Values": [
          {
            "$type": "RPG.GameCore.SharedString, RPG.GameCore.Config",
            "Key": "PlayMunicipalChatPath",
            "Value": "Config/Level/MunicipalChatConfig/F20002001/MunicipalChatConfig_F20002001_0006.json"
          },
          {
            "$type": "RPG.GameCore.SharedString, RPG.GameCore.Config",
            "Key": "PlayMunicipalChatName",
            "Value": "MunicipalChatConfig_F20002001_0006"
          },
          {
            "$type": "RPG.GameCore.SharedJsonConfigList, RPG.GameCore.Config",
            "Key": "PlayMunicipalChatCharacterList",
            "Value": [
              {
                "$type": "RPG.GameCore.MunicipalChatEntityInfo, RPG.GameCore.Config",
                "GroupInstanceID": 400010,
                "UniqueName": "1"
              },
              {
                "$type": "RPG.GameCore.MunicipalChatEntityInfo, RPG.GameCore.Config",
                "GroupInstanceID": 400011,
                "UniqueName": "2"
              }
            ]
          }
        ]
      }
    },
    {
      "BridgeStateRotations": [],
      "CampID": 4,
      "CustomTriggerMap": {},
      "CustomTriggerMapV2": {},
      "DialogueGroups": [],
      "DialogueTriggerAngle": 120,
      "DialogueTriggerSkipFakeAvatar": true,
      "ID": 300010,
      "InitLevelGraph": "Config/Level/CrowdBubble/Crowd_Conversation_Template.json",
      "InteractTitle": {
        "Hash": 371857150
      },
      "IsOverrideInitLevelGraph": true,
      "LookAtPlayerTriggerRadius": 2,
      "Name": "Prop10",
      "OverrideHintRange": -1,
      "OverrideLockRaycastOffset": 1.5,
      "OverrideMapIconType": -1,
      "OverridePropName": {
        "Hash": 371857150
      },
      "OverrideSoundRange": -1,
      "PosX": -4.41,
      "PosY": 18.76,
      "PosZ": -114.89,
      "PropID": 100,
      "RotX": 0.983715,
      "RotY": 3.46659,
      "RotZ": 2.150003,
      "Scale": {
        "magnitude": 1.73205078,
        "normalized": {
          "magnitude": 0.99999994,
          "normalized": {
            "magnitude": 1.00000012,
            "sqrMagnitude": 1.00000024,
            "x": 0.5773503,
            "y": 0.5773503,
            "z": 0.5773503
          },
          "sqrMagnitude": 0.99999994,
          "x": 0.577350259,
          "y": 0.577350259,
          "z": 0.577350259
        },
        "sqrMagnitude": 3,
        "x": 1,
        "y": 1,
        "z": 1
      },
      "ServerInteractVerificationIDList": [],
      "SpawnConfig": {
        "EntitySpawnConfig": {
          "BlackInDistance": 25,
          "NeedBlackIn": true,
          "NeedFadeIn": true,
          "NeedFadeOut": true
        }
      },
      "TalkDialogGroupIDList": [],
      "Trigger": {
        "DimX": 1,
        "DimY": 1,
        "DimZ": 1,
        "PointList": [],
        "Radius": 2
      },
      "TriggerValidGuest": {
        "LocalPlayer": true,
        "Teammember": true
      },
      "ValueSource": {
        "SharedValues": [
          {
            "$type": "RPG.GameCore.SharedString, RPG.GameCore.Config",
            "Key": "PlayPerformanceE",
            "Value": "500061003"
          }
        ],
        "Values": [
          {
            "$type": "RPG.GameCore.SharedString, RPG.GameCore.Config",
            "Key": "PlayPerformanceE",
            "Value": "500061003"
          }
        ]
      }
    }
  ],
  "RandomInit": {
    "ControlList": [
      {
        "ControlID": 1,
        "CrowdIDList": [],
        "NPCIDList": [
          400001,
          400002
        ],
        "PropIDList": [
          300002
        ],
        "Weight": 1
      },
      {
        "ControlID": 1,
        "CrowdIDList": [],
        "NPCIDList": [
          400003,
          400004
        ],
        "PropIDList": [
          300003
        ],
        "Weight": 1
      },
      {
        "ControlID": 1,
        "CrowdIDList": [],
        "NPCIDList": [
          400005,
          400006
        ],
        "PropIDList": [
          300004
        ],
        "Weight": 1
      },
      {
        "ControlID": 2,
        "CrowdIDList": [],
        "NPCIDList": [
          400007,
          400008
        ],
        "PropIDList": [
          300005,
          300008
        ],
        "Weight": 1
      },
      {
        "ControlID": 2,
        "CrowdIDList": [],
        "NPCIDList": [
          400009
        ],
        "PropIDList": [
          300007,
          300009
        ],
        "Weight": 1
      },
      {
        "ControlID": 2,
        "CrowdIDList": [],
        "NPCIDList": [
          400010,
          400011
        ],
        "PropIDList": [
          300006,
          300010
        ],
        "Weight": 1
      }
    ]
  },
  "SaveType": "Reset",
  "SmartObjectList": [],
  "StreamingTemplateType": "Standard",
  "ValueSource": {},
  "WaypointList": []
}