{
  "AnchorList": [],
  "AreaAnchorName": "LevelArea_P10306_F10306001_G130",
  "AudienceList": [],
  "BattleAreaList": [],
  "Category": "Mission",
  "ConflictIDList": [],
  "ConflictWhiteList": [],
  "CrowdList": [],
  "CurveList": [],
  "DistrictList": [],
  "GroupName": "MainMission1034205_29",
  "HoYoGroupType": "Container",
  "IsHoyoGroup": true,
  "LittleGameList": [],
  "MonsterList": [],
  "NPCList": [
    {
      "BoardShowList": [
        1
      ],
      "BornType": "Mission",
      "CameraCenterEntityList": [],
      "CameraConfig": {},
      "DefaultAnimationType": "FreeStyle",
      "DefaultIdleFreeStyleMotionID": 100020000,
      "Dialog": {
        "EnableDialogCamera": true,
        "LevelGraph": "Config/Level/NPCDialogue/P10306/F10306001_G130/DialogueMain_F10306001_G130_N400001.json",
        "PackList": []
      },
      "DialogueGroups": [],
      "DialogueTriggerAngle": 120,
      "DialogueTriggerSkipFakeAvatar": true,
      "DialogueTriggerSkipSpecifiedFakeAvatarList": [],
      "ID": 400001,
      "InitialHiddenNodeList": [],
      "InteractIconType": "ChatIcon",
      "LoadOnInitial": true,
      "NPCID": 13269,
      "Name": "NPC1",
      "OverrideNPCName": {
        "Hash": 1004529292
      },
      "OverrideNPCTitle": {
        "Hash": 371857150
      },
      "OverrideReplaceMaterialKeyList": [],
      "PosX": -52.70299,
      "PosY": 4.89499,
      "PosZ": 179.153,
      "RotY": 129.4618,
      "ServerInteractVerificationIDList": [],
      "SpawnConfig": {
        "CaptureDistanceTolerance": 1.5,
        "EntitySpawnConfig": {
          "BlackInDistance": 25,
          "NeedBlackIn": true,
          "NeedFadeIn": true,
          "NeedFadeOut": true
        },
        "TryCapture": true
      },
      "TalkDialogGroupIDList": [],
      "TriggerValidGuest": {
        "LocalPlayer": true,
        "Teammember": true
      },
      "ValueSource": {}
    },
    {
      "BoardShowList": [],
      "BornType": "Mission",
      "CameraCenterEntityList": [],
      "CameraConfig": {},
      "DefaultAnimationType": "FreeStyle",
      "DefaultIdleFreeStyleMotionID": 313190000,
      "DialogueGroups": [],
      "DialogueTriggerAngle": 120,
      "DialogueTriggerSkipFakeAvatar": true,
      "DialogueTriggerSkipSpecifiedFakeAvatarList": [],
      "ID": 400002,
      "InitialHiddenNodeList": [],
      "InteractIconType": "ChatIcon",
      "LoadOnInitial": true,
      "NPCID": 1319,
      "Name": "NPC2",
      "OverrideNPCName": {
        "Hash": 371857150
      },
      "OverrideNPCTitle": {
        "Hash": 371857150
      },
      "OverrideReplaceMaterialKeyList": [],
      "PosX": -51.88,
      "PosY": 4.876003,
      "PosZ": 178.35,
      "RotY": 325.3265,
      "ServerInteractVerificationIDList": [],
      "SpawnConfig": {
        "CaptureDistanceTolerance": 1.5,
        "EntitySpawnConfig": {
          "BlackInDistance": 25,
          "NeedBlackIn": true,
          "NeedFadeIn": true,
          "NeedFadeOut": true
        },
        "TryCapture": true
      },
      "TalkDialogGroupIDList": [],
      "TriggerValidGuest": {
        "LocalPlayer": true,
        "Teammember": true
      },
      "ValueSource": {}
    }
  ],
  "OwnerMainMissionID": 1034205,
  "PathwayList": [],
  "PedestrianList": [],
  "PedestrianV2List": [],
  "PropList": [],
  "SaveType": "Reset",
  "SmartObjectList": [],
  "StreamingTemplateType": "Standard",
  "ValueSource": {},
  "WaypointList": []
}